MANIFEST.in
setup.py
Monster_ASCII_Game/__init__.py
Monster_ASCII_Game/battle.py
Monster_ASCII_Game/display.py
Monster_ASCII_Game/game.py
Monster_ASCII_Game/monster.py
Monster_ASCII_Game/player.py
Monster_ASCII_Game/trainer.py
Monster_ASCII_Game/Images/b1.png
Monster_ASCII_Game/Images/c1.jpg
Monster_ASCII_Game/Images/c2.png
Monster_ASCII_Game/Images/c3.png
Monster_ASCII_Game/Images/c4.png
Monster_ASCII_Game/Images/f2.png
Monster_ASCII_Game/Images/f3.png
Monster_ASCII_Game/Images/f5.png
Monster_ASCII_Game/Images/f6.png
Monster_ASCII_Game/Images/f7.png
Monster_ASCII_Game/Images/f8.png
Monster_ASCII_Game/Images/fs1.png
Monster_ASCII_Game/Images/pikachu.jpg
Monster_ASCII_Game/Images/pokemon red blue.png
Monster_ASCII_Game/Images/recurse.png
Monster_ASCII_Game/Images/s1.gif
Monster_ASCII_Game/Images/s2.png
Monster_ASCII_Game/Images/s3.png
Monster_ASCII_Game/Images/s4.png
Monster_ASCII_Game/Images/s5.png
Monster_ASCII_Game/Images/t1.png
Monster_ASCII_Game/Images/t2.jpg
Monster_ASCII_Game/Images/t3.png
Monster_ASCII_Game/Images/t4.png
Monster_ASCII_Game/Images/title.png
Monster_ASCII_Game/Images/title2.png
Monster_ASCII_Game/Images/trainer.txt
asciimon.egg-info/PKG-INFO
asciimon.egg-info/SOURCES.txt
asciimon.egg-info/dependency_links.txt
asciimon.egg-info/entry_points.txt
asciimon.egg-info/not-zip-safe
asciimon.egg-info/requires.txt
asciimon.egg-info/top_level.txt