Metadata-Version: 1.0
Name: asciimon
Version: 0.1.0
Summary: ASCII Art Monster battle game
Home-page: https://github.com/lauryndbrown/Monster_ASCII_Game
Author: Lauryn Brown
Author-email: lauryndbrown@gmail.com
License: GNU GPLv3
Platform: UNKNOWN
